Tornado_werobot.py
setup.cfg
setup.py
Tornado_WeRoBot.egg-info/PKG-INFO
Tornado_WeRoBot.egg-info/SOURCES.txt
Tornado_WeRoBot.egg-info/dependency_links.txt
Tornado_WeRoBot.egg-info/not-zip-safe
Tornado_WeRoBot.egg-info/requires.txt
Tornado_WeRoBot.egg-info/top_level.txt