Metadata-Version: 1.1
Name: Tornado-WeRoBot
Version: 0.2.0
Summary: Writing WeChat Robot by WeRoBot in Tornado.
Home-page: https://github.com/whtsky/Tornado-WeRoBot
Author: whtsky
Author-email: whtsky@gmail.com
License: BSD
Platform: any
Classifier: Environment :: Web Environment
Classifier: Intended Audience :: Developers
Classifier: License :: OSI Approved :: BSD License
Classifier: Operating System :: OS Independent
Classifier: Programming Language :: Python
Classifier: Topic :: Internet :: WWW/HTTP :: Dynamic Content
Classifier: Topic :: Software Development :: Libraries :: Python Modules
